{
  "_class": "group",
  "booleanOperation": 0,
  "clippingMaskMode": 0,
  "do_objectID": "16017ED5-E62C-4A6C-A311-AD9E0C1BB261",
  "exportOptions": {
    "_class": "exportOptions",
    "do_objectID": "934B4F14-7182-4C00-9FA3-63B046C093B5",
    "exportFormats": [
      {
        "_class": "exportFormat",
        "absoluteSize": 0,
        "fileFormat": "png",
        "name": "mdpi/",
        "namingScheme": 1,
        "scale": 1,
        "visibleScaleType": 0
      },
      {
        "_class": "exportFormat",
        "absoluteSize": 0,
        "fileFormat": "png",
        "name": "hdpi/",
        "namingScheme": 1,
        "scale": 1.5,
        "visibleScaleType": 0
      },
      {
        "_class": "exportFormat",
        "absoluteSize": 0,
        "fileFormat": "png",
        "name": "xhdpi/",
        "namingScheme": 1,
        "scale": 2,
        "visibleScaleType": 0
      },
      {
        "_class": "exportFormat",
        "absoluteSize": 0,
        "fileFormat": "png",
        "name": "xxhdpi/",
        "namingScheme": 1,
        "scale": 3,
        "visibleScaleType": 0
      },
      {
        "_class": "exportFormat",
        "absoluteSize": 0,
        "fileFormat": "png",
        "name": "xxxhdpi/",
        "namingScheme": 1,
        "scale": 4,
        "visibleScaleType": 0
      }
    ],
    "includedLayerIds": [
    ],
    "layerOptions": 0,
    "shouldTrim": false
  },
  "frame": {
    "_class": "rect",
    "constrainProportions": false,
    "do_objectID": "857B507F-B764-417D-A640-F85A8CB20151",
    "height": 24,
    "width": 24,
    "x": 0,
    "y": 0
  },
  "hasClickThrough": false,
  "hasClippingMask": false,
  "isFixedToViewport": false,
  "isFlippedHorizontal": false,
  "isFlippedVertical": false,
  "isLocked": false,
  "isVisible": true,
  "layerListExpandedType": 0,
  "layers": [
    {
      "class": "group",
      "id": "8E646FBD-1710-49FF-A99B-154FCAD80079"
    },
    {
      "class": "group",
      "id": "9E844F95-FB95-4173-8580-8ED047F6FDB4"
    }
  ],
  "name": "round-delete-24px",
  "nameIsFixed": false,
  "resizingConstraint": 63,
  "resizingType": 0,
  "rotation": 0,
  "shouldBreakMaskChain": false,
  "style": {
    "_class": "style",
    "do_objectID": "28F19D67-8A36-407E-968C-6F7432D34B0E",
    "endMarkerType": 0,
    "miterLimit": 10,
    "startMarkerType": 0,
    "windingRule": 1
  }
}