{
  "_class": "symbolInstance",
  "booleanOperation": -1,
  "clippingMaskMode": 0,
  "do_objectID": "FE5A19B3-9B8D-477F-8451-F53DD87BF7D6",
  "exportOptions": {
    "_class": "exportOptions",
    "do_objectID": "F83A1421-B90C-4D50-BC6C-59F76D0700D3",
    "exportFormats": [
      {
        "_class": "exportFormat",
        "absoluteSize": 0,
        "fileFormat": "png",
        "name": "mdpi/",
        "namingScheme": 1,
        "scale": 1,
        "visibleScaleType": 0
      },
      {
        "_class": "exportFormat",
        "absoluteSize": 0,
        "fileFormat": "png",
        "name": "hdpi/",
        "namingScheme": 1,
        "scale": 1.5,
        "visibleScaleType": 0
      },
      {
        "_class": "exportFormat",
        "absoluteSize": 0,
        "fileFormat": "png",
        "name": "xhdpi/",
        "namingScheme": 1,
        "scale": 2,
        "visibleScaleType": 0
      },
      {
        "_class": "exportFormat",
        "absoluteSize": 0,
        "fileFormat": "png",
        "name": "xxhdpi/",
        "namingScheme": 1,
        "scale": 3,
        "visibleScaleType": 0
      },
      {
        "_class": "exportFormat",
        "absoluteSize": 0,
        "fileFormat": "png",
        "name": "xxxhdpi/",
        "namingScheme": 1,
        "scale": 4,
        "visibleScaleType": 0
      }
    ],
    "includedLayerIds": [
    ],
    "layerOptions": 0,
    "shouldTrim": false
  },
  "frame": {
    "_class": "rect",
    "constrainProportions": false,
    "do_objectID": "C9EF097A-0D84-4C06-9464-A9617B21DD1E",
    "height": 178,
    "width": 360,
    "x": 0,
    "y": 290
  },
  "hasClippingMask": false,
  "horizontalSpacing": 0,
  "isFixedToViewport": false,
  "isFlippedHorizontal": false,
  "isFlippedVertical": false,
  "isLocked": false,
  "isVisible": true,
  "layerListExpandedType": 0,
  "name": "feedItemCard / comps / image_rect_3",
  "nameIsFixed": false,
  "overrideValues": [
    {
      "_class": "overrideValue",
      "do_objectID": "A05AACF0-0CCB-42B7-A45F-0D2FEC4B6543",
      "overrideName": "96B16626-A9F2-45E1-BC28-B36E365A3788_image",
      "value": {
        "_class": "MSJSONFileReference",
        "_ref": "images/60c601f8c9172c5defb089562593029220fbd177.png",
        "_ref_class": "MSImageData"
      }
    },
    {
      "_class": "overrideValue",
      "do_objectID": "DD2F7C75-23DC-4D03-B702-56886B3EDF53",
      "overrideName": "00EE0EEB-321C-4EEE-B066-B50461E60BA4_image",
      "value": {
        "_class": "MSJSONFileReference",
        "_ref": "images/9c1f9cc6fa9fbcd5e4229ebb5aec1efddc65ddb2.png",
        "_ref_class": "MSImageData"
      }
    }
  ],
  "resizingConstraint": 63,
  "resizingType": 0,
  "rotation": 0,
  "scale": 1,
  "shouldBreakMaskChain": false,
  "style": {
    "_class": "style",
    "do_objectID": "F9072B3D-22A7-4DA7-888A-E82FCF9D7AF0",
    "endMarkerType": 0,
    "miterLimit": 10,
    "startMarkerType": 0,
    "windingRule": 1
  },
  "symbolID": "C23857B5-B24C-4CF6-8714-D7C74425CA18",
  "verticalSpacing": 0
}