{
  "_class": "group",
  "booleanOperation": -1,
  "do_objectID": "5256915B-2F4D-450F-B43A-DBE5FEFC5576",
  "exportOptions": {
    "_class": "exportOptions",
    "do_objectID": "CB63512E-EFFA-4C92-A66C-F776DFB54FA0",
    "exportFormats": [
      {
        "_class": "exportFormat",
        "absoluteSize": 0,
        "fileFormat": "eps",
        "name": "",
        "namingScheme": 0,
        "scale": 4,
        "visibleScaleType": 0
      }
    ],
    "includedLayerIds": [
    ],
    "layerOptions": 0,
    "shouldTrim": false
  },
  "frame": {
    "_class": "rect",
    "constrainProportions": false,
    "do_objectID": "D1938617-380E-4CAB-8EC8-948D261B7122",
    "height": 640,
    "width": 296,
    "x": 381,
    "y": 67
  },
  "hasClickThrough": false,
  "isFixedToViewport": false,
  "isFlippedHorizontal": false,
  "isFlippedVertical": false,
  "isLocked": false,
  "isVisible": true,
  "layerListExpandedType": 2,
  "layers": [
    {
      "class": "group",
      "id": "1CBA8EBA-C76A-46EB-B5E9-FD3C46900A02"
    }
  ],
  "name": "7",
  "nameIsFixed": true,
  "resizingConstraint": 63,
  "resizingType": 0,
  "rotation": 0,
  "shouldBreakMaskChain": false,
  "style": {
    "_class": "style",
    "do_objectID": "76F467C9-6ADF-4F37-A39B-8C182C524123",
    "endMarkerType": 0,
    "miterLimit": 10,
    "startMarkerType": 0,
    "windingRule": 1
  }
}