{
  "_class": "symbolMaster",
  "backgroundColor": {
    "_class": "color",
    "alpha": 1,
    "blue": 1,
    "do_objectID": "98883074-103F-4803-AA67-C621A17FEED6",
    "green": 1,
    "red": 1
  },
  "booleanOperation": 0,
  "changeIdentifier": 4172,
  "clippingMaskMode": 0,
  "do_objectID": "2CDA5C18-019F-41EC-BEEC-C62C4E54851C",
  "exportOptions": {
    "_class": "exportOptions",
    "do_objectID": "A32C747A-B293-481A-A08E-424849B3545F",
    "exportFormats": [
      {
        "_class": "exportFormat",
        "absoluteSize": 0,
        "fileFormat": "png",
        "name": "mdpi/",
        "namingScheme": 1,
        "scale": 1,
        "visibleScaleType": 0
      },
      {
        "_class": "exportFormat",
        "absoluteSize": 0,
        "fileFormat": "png",
        "name": "hdpi/",
        "namingScheme": 1,
        "scale": 1.5,
        "visibleScaleType": 0
      },
      {
        "_class": "exportFormat",
        "absoluteSize": 0,
        "fileFormat": "png",
        "name": "xhdpi/",
        "namingScheme": 1,
        "scale": 2,
        "visibleScaleType": 0
      },
      {
        "_class": "exportFormat",
        "absoluteSize": 0,
        "fileFormat": "png",
        "name": "xxhdpi/",
        "namingScheme": 1,
        "scale": 3,
        "visibleScaleType": 0
      },
      {
        "_class": "exportFormat",
        "absoluteSize": 0,
        "fileFormat": "png",
        "name": "xxxhdpi/",
        "namingScheme": 1,
        "scale": 4,
        "visibleScaleType": 0
      }
    ],
    "includedLayerIds": [
    ],
    "layerOptions": 0,
    "shouldTrim": false
  },
  "frame": {
    "_class": "rect",
    "constrainProportions": false,
    "do_objectID": "C9A62D87-E6FC-4EA2-808E-69C70B487836",
    "height": 24,
    "width": 360,
    "x": 1802,
    "y": 249
  },
  "groupLayout": {
    "_class": "MSImmutableFreeformGroupLayout"
  },
  "hasBackgroundColor": false,
  "hasClickThrough": true,
  "hasClippingMask": false,
  "horizontalRulerData": {
    "_class": "rulerData",
    "base": 0,
    "do_objectID": "C6B8157A-B56A-4841-BD3C-499E39A90B83",
    "guides": [
    ]
  },
  "includeBackgroundColorInExport": true,
  "includeBackgroundColorInInstance": false,
  "includeInCloudUpload": true,
  "isFixedToViewport": false,
  "isFlippedHorizontal": false,
  "isFlippedVertical": false,
  "isFlowHome": false,
  "isLocked": false,
  "isVisible": true,
  "layerListExpandedType": 0,
  "layers": [
    {
      "class": "rectangle",
      "id": "0E4A4EFD-8108-4E61-9904-8C6B038D94D2"
    },
    {
      "class": "text",
      "id": "E551079A-C721-4315-87EF-2D16EE7F3761"
    }
  ],
  "name": "snackbar / connected",
  "nameIsFixed": true,
  "overrideProperties": [
    {
      "_class": "MSImmutableOverrideProperty",
      "canOverride": true,
      "overrideName": "E551079A-C721-4315-87EF-2D16EE7F3761_stringValue"
    }
  ],
  "resizesContent": true,
  "resizingConstraint": 63,
  "resizingType": 0,
  "rotation": 0,
  "shouldBreakMaskChain": true,
  "style": {
    "_class": "style",
    "do_objectID": "9CD00A53-ABAC-4987-A07C-2FA19FC08089",
    "endMarkerType": 0,
    "miterLimit": 10,
    "startMarkerType": 0,
    "windingRule": 1
  },
  "symbolID": "0A33B324-9534-48EC-AE40-807A95C3A259",
  "verticalRulerData": {
    "_class": "rulerData",
    "base": 0,
    "do_objectID": "A0B3981C-DE02-488B-974D-E554097BD396",
    "guides": [
    ]
  }
}