{
  "_class": "symbolInstance",
  "booleanOperation": 0,
  "do_objectID": "8822BF24-D47B-4117-A06A-DC6F87D9C500",
  "exportOptions": {
    "_class": "exportOptions",
    "do_objectID": "40FF5D00-04AE-4A41-9578-61B844573E63",
    "exportFormats": [
      {
        "_class": "exportFormat",
        "absoluteSize": 0,
        "fileFormat": "png",
        "name": "mdpi/",
        "namingScheme": 1,
        "scale": 1,
        "visibleScaleType": 0
      },
      {
        "_class": "exportFormat",
        "absoluteSize": 0,
        "fileFormat": "png",
        "name": "hdpi/",
        "namingScheme": 1,
        "scale": 1.5,
        "visibleScaleType": 0
      },
      {
        "_class": "exportFormat",
        "absoluteSize": 0,
        "fileFormat": "png",
        "name": "xhdpi/",
        "namingScheme": 1,
        "scale": 2,
        "visibleScaleType": 0
      },
      {
        "_class": "exportFormat",
        "absoluteSize": 0,
        "fileFormat": "png",
        "name": "xxhdpi/",
        "namingScheme": 1,
        "scale": 3,
        "visibleScaleType": 0
      },
      {
        "_class": "exportFormat",
        "absoluteSize": 0,
        "fileFormat": "png",
        "name": "xxxhdpi/",
        "namingScheme": 1,
        "scale": 4,
        "visibleScaleType": 0
      }
    ],
    "includedLayerIds": [
    ],
    "layerOptions": 0,
    "shouldTrim": false
  },
  "frame": {
    "_class": "rect",
    "constrainProportions": false,
    "do_objectID": "029FCBC1-371F-4D68-8434-0043FE0994A4",
    "height": 40,
    "width": 124,
    "x": 0,
    "y": 0
  },
  "horizontalSpacing": 0,
  "isFixedToViewport": false,
  "isFlippedHorizontal": false,
  "isFlippedVertical": false,
  "isLocked": false,
  "isVisible": true,
  "layerListExpandedType": 0,
  "name": "writePost / boxBase",
  "nameIsFixed": false,
  "overrideValues": [
  ],
  "resizingConstraint": 63,
  "resizingType": 0,
  "rotation": 0,
  "scale": 1,
  "shouldBreakMaskChain": false,
  "style": {
    "_class": "style",
    "do_objectID": "7453D936-303B-4AB3-8940-F85A307A4286",
    "endMarkerType": 0,
    "miterLimit": 10,
    "startMarkerType": 0,
    "windingRule": 1
  },
  "symbolID": "78B5DF35-BDC0-4A6D-8F89-E03F5F7B7705",
  "verticalSpacing": 0
}