{
  "_class": "shapePath",
  "booleanOperation": -1,
  "do_objectID": "E31DC57D-1386-40AC-A336-4A793FB669F9",
  "edited": true,
  "exportOptions": {
    "_class": "exportOptions",
    "exportFormats": [
    ],
    "includedLayerIds": [
    ],
    "layerOptions": 0,
    "shouldTrim": false
  },
  "frame": {
    "_class": "rect",
    "constrainProportions": false,
    "height": 8.092367187499997,
    "width": 8.190422535211265,
    "x": 20.15954929577465,
    "y": 28.60034375
  },
  "isClosed": true,
  "isFixedToViewport": false,
  "isFlippedHorizontal": false,
  "isFlippedVertical": false,
  "isLocked": false,
  "isVisible": true,
  "layerListExpandedType": 0,
  "name": "Path",
  "nameIsFixed": false,
  "pointRadiusBehaviour": 1,
  "points": [
    {
      "_class": "curvePoint",
      "cornerRadius": 0,
      "curveFrom": "{1, 0.77570299172735091}",
      "curveMode": 2,
      "curveTo": "{1, 0.22430617972375586}",
      "hasCurveFrom": true,
      "hasCurveTo": true,
      "point": "{1, 0.5}"
    },
    {
      "_class": "curvePoint",
      "cornerRadius": 0,
      "curveFrom": "{0.22429495116247086, 1}",
      "curveMode": 2,
      "curveTo": "{0.77571422020452163, 1}",
      "hasCurveFrom": true,
      "hasCurveTo": true,
      "point": "{0.50000458568349626, 1}"
    },
    {
      "_class": "curvePoint",
      "cornerRadius": 0,
      "curveFrom": "{0, 0.22429700827264906}",
      "curveMode": 2,
      "curveTo": "{0, 0.77569382027624412}",
      "hasCurveFrom": true,
      "hasCurveTo": true,
      "point": "{0, 0.5}"
    },
    {
      "_class": "curvePoint",
      "cornerRadius": 0,
      "curveFrom": "{0.77570504883752966, 0}",
      "curveMode": 2,
      "curveTo": "{0.22430412252946291, 0}",
      "hasCurveFrom": true,
      "hasCurveTo": true,
      "point": "{0.50000458568349626, 0}"
    }
  ],
  "resizingConstraint": 63,
  "resizingType": 0,
  "rotation": 0,
  "shouldBreakMaskChain": false
}