{
  "_class": "artboard",
  "backgroundColor": {
    "_class": "color",
    "alpha": 1,
    "blue": 1,
    "green": 1,
    "red": 1
  },
  "booleanOperation": 0,
  "clippingMaskMode": 0,
  "do_objectID": "8DC5D65B-3022-4B36-881C-E08CAC40FB40",
  "exportOptions": {
    "_class": "exportOptions",
    "exportFormats": [
      {
        "_class": "exportFormat",
        "absoluteSize": 0,
        "fileFormat": "png",
        "name": "",
        "namingScheme": 0,
        "scale": 1,
        "visibleScaleType": 0
      },
      {
        "_class": "exportFormat",
        "absoluteSize": 0,
        "fileFormat": "png",
        "name": "@2x",
        "namingScheme": 0,
        "scale": 2,
        "visibleScaleType": 0
      },
      {
        "_class": "exportFormat",
        "absoluteSize": 0,
        "fileFormat": "png",
        "name": "@3x",
        "namingScheme": 0,
        "scale": 3,
        "visibleScaleType": 0
      }
    ],
    "includedLayerIds": [
    ],
    "layerOptions": 0,
    "shouldTrim": false
  },
  "frame": {
    "_class": "rect",
    "constrainProportions": false,
    "height": 812,
    "width": 375,
    "x": -1738,
    "y": -1606
  },
  "hasBackgroundColor": false,
  "hasClickThrough": true,
  "hasClippingMask": false,
  "horizontalRulerData": {
    "_class": "rulerData",
    "base": 0,
    "guides": [
    ]
  },
  "includeBackgroundColorInExport": true,
  "includeInCloudUpload": true,
  "isFixedToViewport": false,
  "isFlippedHorizontal": false,
  "isFlippedVertical": false,
  "isFlowHome": false,
  "isLocked": false,
  "isVisible": true,
  "layerListExpandedType": 2,
  "layers": [
    {
      "class": "symbolInstance",
      "id": "235F1C88-DE4A-4230-BA67-9CA0A251C4AC"
    },
    {
      "class": "text",
      "id": "423F17E7-81E5-48D8-AEC2-83E6C8F617F5"
    },
    {
      "class": "symbolInstance",
      "id": "31C2560C-D02E-42D9-A429-A115C9083486"
    },
    {
      "class": "symbolInstance",
      "id": "773C8FF0-5B61-4575-BD94-1FDC5B1C05F0"
    },
    {
      "class": "symbolInstance",
      "id": "ED5F6224-80BF-4418-9DF4-7EAE0D2D693D"
    },
    {
      "class": "symbolInstance",
      "id": "96ED5AEF-A087-4A36-AC89-73C691FBD4E5"
    },
    {
      "class": "symbolInstance",
      "id": "BE895622-4013-4015-BF4B-FB35EAE90583"
    },
    {
      "class": "symbolInstance",
      "id": "9751E6BB-3CC3-44D0-8412-E2BD3BFB3504"
    },
    {
      "class": "symbolInstance",
      "id": "2330699E-F0BD-436D-BF18-B8AC76DD05D5"
    },
    {
      "class": "symbolInstance",
      "id": "30C8AF8B-A8DB-4D66-8C4B-CC2FD2D6DF29"
    },
    {
      "class": "symbolInstance",
      "id": "759CA68B-982F-4EA6-8EEB-7D7631701F2D"
    },
    {
      "class": "symbolInstance",
      "id": "BD731304-42D8-42C9-B497-B6AB1A016272"
    },
    {
      "class": "symbolInstance",
      "id": "EB76F8F2-E748-48C0-9A7E-83F0847B3731"
    },
    {
      "class": "symbolInstance",
      "id": "F903AFA5-4213-43C6-9426-792112D91D70"
    },
    {
      "class": "symbolInstance",
      "id": "A92DAD54-A3E4-43FA-92C8-5C97860802AB"
    }
  ],
  "name": "[iPhoneX] postDetailViewComment - seeMore - 2",
  "nameIsFixed": true,
  "presetDictionary": {
    "allowResizedMatching": 1,
    "height": 812,
    "name": "iPhone X",
    "offersLandscapeVariant": 1,
    "width": 375
  },
  "resizesContent": false,
  "resizingConstraint": 63,
  "resizingType": 0,
  "rotation": 0,
  "shouldBreakMaskChain": true,
  "style": {
    "_class": "style",
    "endMarkerType": 0,
    "miterLimit": 10,
    "startMarkerType": 0,
    "windingRule": 1
  },
  "verticalRulerData": {
    "_class": "rulerData",
    "base": 0,
    "guides": [
    ]
  }
}