{
  "_class": "symbolInstance",
  "booleanOperation": 0,
  "clippingMaskMode": 0,
  "do_objectID": "2F41627F-3D83-4A7D-B68D-987827043CDE",
  "exportOptions": {
    "_class": "exportOptions",
    "do_objectID": "06C39AB4-782C-4F96-B639-FA8D0BC1558B",
    "exportFormats": [
      {
        "_class": "exportFormat",
        "absoluteSize": 0,
        "fileFormat": "png",
        "name": "",
        "namingScheme": 0,
        "scale": 1,
        "visibleScaleType": 0
      },
      {
        "_class": "exportFormat",
        "absoluteSize": 0,
        "fileFormat": "png",
        "name": "@2x",
        "namingScheme": 0,
        "scale": 2,
        "visibleScaleType": 0
      },
      {
        "_class": "exportFormat",
        "absoluteSize": 0,
        "fileFormat": "png",
        "name": "@3x",
        "namingScheme": 0,
        "scale": 3,
        "visibleScaleType": 0
      }
    ],
    "includedLayerIds": [
    ],
    "layerOptions": 0,
    "shouldTrim": false
  },
  "frame": {
    "_class": "rect",
    "constrainProportions": false,
    "do_objectID": "3044C3B1-FACB-449F-A5C3-D5E1A2A22127",
    "height": 48,
    "width": 375,
    "x": 0,
    "y": 20
  },
  "hasClippingMask": false,
  "horizontalSpacing": 0,
  "isFixedToViewport": false,
  "isFlippedHorizontal": false,
  "isFlippedVertical": false,
  "isLocked": false,
  "isVisible": true,
  "layerListExpandedType": 0,
  "name": "headerBase3Next",
  "nameIsFixed": true,
  "originalObjectID": "2835B45C-CA49-4189-B722-C5945D45CFBB",
  "overrideValues": [
    {
      "_class": "overrideValue",
      "do_objectID": "E789DC6E-0FD6-40A7-AD19-A96CE1404215",
      "overrideName": "6EACD343-9ABE-4B1F-925F-C58B253A8386_symbolID",
      "value": "A9A66BDC-E29C-4AA0-8D2B-B5D27A66366F"
    },
    {
      "_class": "overrideValue",
      "do_objectID": "5BF1E528-1E50-41EA-9DBA-354CB7447E5D",
      "overrideName": "57BB91F6-2A8F-4085-AF8C-77DD94BD41D0_stringValue",
      "value": "재요청"
    },
    {
      "_class": "overrideValue",
      "do_objectID": "DEC1C896-E637-4F1E-BBDC-61868FE6104D",
      "overrideName": "28BA8995-3C75-4D56-B969-9FA88FBC845E_stringValue",
      "value": " "
    }
  ],
  "resizingConstraint": 63,
  "resizingType": 0,
  "rotation": 0,
  "scale": 1,
  "shouldBreakMaskChain": false,
  "style": {
    "_class": "style",
    "do_objectID": "FB4E70EF-0421-4DB7-81CC-576557603449",
    "endMarkerType": 0,
    "miterLimit": 10,
    "startMarkerType": 0,
    "windingRule": 1
  },
  "symbolID": "6EF24636-19B7-4F02-A8A6-3837FD8E8173",
  "verticalSpacing": 0
}