{
  "_class": "symbolInstance",
  "booleanOperation": 0,
  "clippingMaskMode": 0,
  "do_objectID": "6B8BBE32-3074-499A-B5E2-FE653721DC16",
  "exportOptions": {
    "_class": "exportOptions",
    "do_objectID": "EAAF8E4A-EF60-4173-9546-902F9E2ADDA5",
    "exportFormats": [
      {
        "_class": "exportFormat",
        "absoluteSize": 0,
        "fileFormat": "png",
        "name": "",
        "namingScheme": 0,
        "scale": 1,
        "visibleScaleType": 0
      },
      {
        "_class": "exportFormat",
        "absoluteSize": 0,
        "fileFormat": "png",
        "name": "@2x",
        "namingScheme": 0,
        "scale": 2,
        "visibleScaleType": 0
      },
      {
        "_class": "exportFormat",
        "absoluteSize": 0,
        "fileFormat": "png",
        "name": "@3x",
        "namingScheme": 0,
        "scale": 3,
        "visibleScaleType": 0
      }
    ],
    "includedLayerIds": [
    ],
    "layerOptions": 0,
    "shouldTrim": false
  },
  "frame": {
    "_class": "rect",
    "constrainProportions": false,
    "do_objectID": "505A330B-09F1-4A74-9AEA-90B43CFF08E2",
    "height": 80,
    "width": 375,
    "x": 0,
    "y": 698
  },
  "hasClippingMask": false,
  "horizontalSpacing": 0,
  "isFixedToViewport": false,
  "isFlippedHorizontal": false,
  "isFlippedVertical": false,
  "isLocked": false,
  "isVisible": true,
  "layerListExpandedType": 0,
  "name": "asBound / basicIcon",
  "nameIsFixed": false,
  "originalObjectID": "F7F5E249-BF31-447E-A8B6-72ACDE779163",
  "overrideValues": [
    {
      "_class": "overrideValue",
      "do_objectID": "99F6AD0B-BEC1-4970-B9A2-473A69C49591",
      "overrideName": "51CA925F-E678-40B3-A388-8396677E41AE_stringValue",
      "value": "게시글 삭제하기"
    }
  ],
  "resizingConstraint": 63,
  "resizingType": 0,
  "rotation": 0,
  "scale": 1,
  "shouldBreakMaskChain": false,
  "style": {
    "_class": "style",
    "do_objectID": "BC59FC45-B40F-40FF-A108-340F850EB848",
    "endMarkerType": 0,
    "miterLimit": 10,
    "startMarkerType": 0,
    "windingRule": 1
  },
  "symbolID": "298623A1-EE17-43D6-A850-E89E4CDA847B",
  "verticalSpacing": 0
}