{
  "_class": "artboard",
  "backgroundColor": {
    "_class": "color",
    "alpha": 1,
    "blue": 0.3764706,
    "green": 0.7529412,
    "red": 0.09019608
  },
  "booleanOperation": 0,
  "clippingMaskMode": 0,
  "do_objectID": "9D2E8580-5461-4C61-87AE-705F818F2504",
  "exportOptions": {
    "_class": "exportOptions",
    "exportFormats": [
      {
        "_class": "exportFormat",
        "absoluteSize": 0,
        "fileFormat": "png",
        "name": "mdpi/",
        "namingScheme": 1,
        "scale": 1,
        "visibleScaleType": 0
      },
      {
        "_class": "exportFormat",
        "absoluteSize": 0,
        "fileFormat": "png",
        "name": "hdpi/",
        "namingScheme": 1,
        "scale": 1.5,
        "visibleScaleType": 0
      },
      {
        "_class": "exportFormat",
        "absoluteSize": 0,
        "fileFormat": "png",
        "name": "xhdpi/",
        "namingScheme": 1,
        "scale": 2,
        "visibleScaleType": 0
      },
      {
        "_class": "exportFormat",
        "absoluteSize": 0,
        "fileFormat": "png",
        "name": "xxhdpi/",
        "namingScheme": 1,
        "scale": 3,
        "visibleScaleType": 0
      },
      {
        "_class": "exportFormat",
        "absoluteSize": 0,
        "fileFormat": "png",
        "name": "xxxhdpi/",
        "namingScheme": 1,
        "scale": 4,
        "visibleScaleType": 0
      }
    ],
    "includedLayerIds": [
    ],
    "layerOptions": 0,
    "shouldTrim": false
  },
  "frame": {
    "_class": "rect",
    "constrainProportions": false,
    "height": 640,
    "width": 360,
    "x": 2026,
    "y": 2259
  },
  "grid": {
    "_class": "simpleGrid",
    "gridSize": 20,
    "isEnabled": false,
    "thickGridTimes": 10
  },
  "hasBackgroundColor": false,
  "hasClickThrough": false,
  "hasClippingMask": false,
  "horizontalRulerData": {
    "_class": "rulerData",
    "base": 0,
    "guides": [
    ]
  },
  "includeBackgroundColorInExport": true,
  "includeInCloudUpload": true,
  "isFixedToViewport": false,
  "isFlippedHorizontal": false,
  "isFlippedVertical": false,
  "isFlowHome": false,
  "isLocked": false,
  "isVisible": true,
  "layerListExpandedType": 0,
  "layers": [
    {
      "class": "rectangle",
      "id": "750AB56E-A065-4442-9455-11717814965E"
    },
    {
      "class": "symbolInstance",
      "id": "00B4FE3E-B8FE-4E0E-ADF4-7566DB3828E9"
    },
    {
      "class": "symbolInstance",
      "id": "55EB5274-4E3E-4FB2-A6D6-B0CD1C3A3593"
    },
    {
      "class": "symbolInstance",
      "id": "B4D9CFE5-0962-4580-84D6-4819BD9A1C09"
    },
    {
      "class": "symbolInstance",
      "id": "7216F86B-BCF2-4728-BFFE-4207AB006679"
    },
    {
      "class": "symbolInstance",
      "id": "50859880-63FD-45FF-BA51-2BF8F14BA3F9"
    },
    {
      "class": "symbolInstance",
      "id": "0E4E835C-C4FC-4E60-8704-1DE2DBA422A7"
    },
    {
      "class": "group",
      "id": "F9C71B0F-B739-4DD6-A7FC-1E504E9E2E89"
    },
    {
      "class": "symbolInstance",
      "id": "E00EA720-7618-47B7-9614-4D2ACA0F1D31"
    },
    {
      "class": "symbolInstance",
      "id": "65F88E82-953B-463D-BD0F-E1923276DDF6"
    },
    {
      "class": "rectangle",
      "id": "059A4D13-D299-4574-96D7-F56A05BD9F53"
    },
    {
      "class": "text",
      "id": "C27D6B65-7F0F-47E7-9410-5B59872317AC"
    },
    {
      "class": "symbolInstance",
      "id": "683CE74D-F1E4-487A-B0FE-87FAFF22ACD5"
    },
    {
      "class": "symbolInstance",
      "id": "E96851D6-79DB-46A9-848B-3344C26737C7"
    }
  ],
  "name": "getUserLocation-search-popup-swipe",
  "nameIsFixed": true,
  "presetDictionary": {
    "allowResizedMatching": 0,
    "height": 640,
    "name": "Mobile",
    "offersLandscapeVariant": 1,
    "width": 360
  },
  "resizesContent": false,
  "resizingConstraint": 63,
  "resizingType": 0,
  "rotation": 0,
  "shouldBreakMaskChain": true,
  "style": {
    "_class": "style",
    "endMarkerType": 0,
    "fills": [
      {
        "_class": "fill",
        "color": {
          "_class": "color",
          "alpha": 1,
          "blue": 1,
          "green": 1,
          "red": 1
        },
        "fillType": 0,
        "gradient": {
          "_class": "gradient",
          "elipseLength": 0,
          "from": "{0.5, 0}",
          "gradientType": 0,
          "stops": [
            {
              "_class": "gradientStop",
              "color": {
                "_class": "color",
                "alpha": 1,
                "blue": 1,
                "green": 1,
                "red": 1
              },
              "position": 0
            },
            {
              "_class": "gradientStop",
              "color": {
                "_class": "color",
                "alpha": 1,
                "blue": 0.2,
                "green": 0.2,
                "red": 0.2
              },
              "position": 1
            }
          ],
          "to": "{0.5, 1}"
        },
        "isEnabled": true,
        "noiseIndex": 0,
        "noiseIntensity": 0,
        "patternFillType": 1,
        "patternTileScale": 1
      }
    ],
    "miterLimit": 10,
    "startMarkerType": 0,
    "windingRule": 1
  },
  "userInfo": {
    "avocode": {
      "idsFixed": 1
    }
  },
  "verticalRulerData": {
    "_class": "rulerData",
    "base": 0,
    "guides": [
    ]
  }
}